AUTHORS.rst
CONTRIBUTING.rst
HISTORY.rst
LICENSE
MANIFEST.in
README.rst
requirements.txt
requirements_dev.txt
setup.cfg
setup.py
docs/Makefile
docs/authors.rst
docs/conf.py
docs/contributing.rst
docs/etcdb.execute.ddl.rst
docs/etcdb.execute.dml.rst
docs/etcdb.execute.rst
docs/etcdb.log.rst
docs/etcdb.rst
docs/etcdb.sqlparser.rst
docs/history.rst
docs/index.rst
docs/installation.rst
docs/make.bat
docs/modules.rst
docs/readme.rst
docs/usage.rst
etcdb/__init__.py
etcdb/cli.py
etcdb/connection.py
etcdb/cursor.py
etcdb/etcddate.py
etcdb/etcdstring.py
etcdb/etcdtime.py
etcdb/etcdtimestamp.py
etcdb/eval_expr.py
etcdb/exception.py
etcdb/lock.py
etcdb/resultset.py
etcdb.egg-info/PKG-INFO
etcdb.egg-info/SOURCES.txt
etcdb.egg-info/dependency_links.txt
etcdb.egg-info/entry_points.txt
etcdb.egg-info/not-zip-safe
etcdb.egg-info/requires.txt
etcdb.egg-info/top_level.txt
etcdb/execute/__init__.py
etcdb/execute/ddl/__init__.py
etcdb/execute/ddl/create.py
etcdb/execute/ddl/drop.py
etcdb/execute/dml/__init__.py
etcdb/execute/dml/delete.py
etcdb/execute/dml/insert.py
etcdb/execute/dml/select.py
etcdb/execute/dml/show.py
etcdb/execute/dml/update.py
etcdb/execute/dml/use.py
etcdb/execute/dml/wait.py
etcdb/log/__init__.py
etcdb/sqlparser/__init__.py
etcdb/sqlparser/etcdb_lexer.py
etcdb/sqlparser/parser.py
etcdb/sqlparser/parsetab.py
etcdb/sqlparser/sql_tree.py
tests/__init__.py
tests/functional/__init__.py
tests/functional/conftest.py
tests/functional/test_etcdb.py
tests/functional/test_lock.py
tests/functional/dml/__init__.py
tests/functional/dml/test_insert.py
tests/functional/dml/test_update.py
tests/unit/__init__.py
tests/unit/conftest.py
tests/unit/test_cli.py
tests/unit/test_cursor.py
tests/unit/test_etcdb.py
tests/unit/test_parser.py
tests/unit/test_resultset.py
tests/unit/execute/__init__.py
tests/unit/execute/test_eval_expr.py
tests/unit/execute/test_eval_identifier.py
tests/unit/execute/ddl/__init__.py
tests/unit/execute/ddl/test_create.py
tests/unit/execute/ddl/test_drop.py
tests/unit/execute/dml/__init__.py
tests/unit/execute/dml/test_insert.py
tests/unit/execute/dml/test_select.py
tests/unit/execute/dml/test_show.py
tests/unit/execute/dml/test_update.py
