Metadata-Version: 1.1
Name: etcdb
Version: 1.7.0
Summary: PEP 249 compatible driver for Etcd
Home-page: https://github.com/box/etcdb
Author: Box TechOps Database Team
Author-email: oss@box.com
License: UNKNOWN
Keywords: etcdb
Platform: UNKNOWN
Classifier: Development Status :: 2 - Pre-Alpha
Classifier: Intended Audience :: Developers
Classifier: Natural Language :: English
Classifier: Programming Language :: Python :: 2
Classifier: Programming Language :: Python :: 2.7
